tests/__init__.py
tests/test_valuelock.py
valuelock/__init__.py
valuelock/valuelock.py
valuelock-0.1.0.dist-info/LICENSE
valuelock-0.1.0.dist-info/METADATA
valuelock-0.1.0.dist-info/WHEEL
valuelock-0.1.0.dist-info/top_level.txt
valuelock-0.1.0.dist-info/RECORD
