Metadata-Version: 2.1
Name: valuelock
Version: 0.1.0
Summary: A Python package for locking based on values.
Home-page: https://github.com/killbus/py-valuelock
Author: killbus
Author-email: killbus@users.noreply.github.com
Classifier: Development Status :: 3 - Alpha
Classifier: Intended Audience :: Developers
Classifier: License :: OSI Approved :: MIT License
Classifier: Programming Language :: Python :: 3
Classifier: Programming Language :: Python :: 3.6
Classifier: Programming Language :: Python :: 3.7
Classifier: Programming Language :: Python :: 3.8
Classifier: Programming Language :: Python :: 3.9
Classifier: Programming Language :: Python :: 3.10
Classifier: Programming Language :: Python :: 3.11
License-File: LICENSE
